photoshop_object_model/__init__.py
photoshop_object_model/actiondescriptor.py
photoshop_object_model/actionlist.py
photoshop_object_model/actionreference.py
photoshop_object_model/application.py
photoshop_object_model/artlayer.py
photoshop_object_model/artlayers.py
photoshop_object_model/batchoptions.py
photoshop_object_model/bitmapconversionoptions.py
photoshop_object_model/bmpsaveoptions.py
photoshop_object_model/camerarawopenoptions.py
photoshop_object_model/channel.py
photoshop_object_model/channels.py
photoshop_object_model/cmykcolor.py
photoshop_object_model/colorsampler.py
photoshop_object_model/colorsamplers.py
photoshop_object_model/contactsheetoptions.py
photoshop_object_model/countitem.py
photoshop_object_model/countitems.py
photoshop_object_model/dicomopenoptions.py
photoshop_object_model/document.py
photoshop_object_model/documentinfo.py
photoshop_object_model/documents.py
photoshop_object_model/epsopenoptions.py
photoshop_object_model/epssaveoptions.py
photoshop_object_model/events.py
photoshop_object_model/exportoptionsillustrator.py
photoshop_object_model/exportoptionssaveforweb.py
photoshop_object_model/gallerybanneroptions.py
photoshop_object_model/gallerycustomcoloroptions.py
photoshop_object_model/galleryimagesoptions.py
photoshop_object_model/galleryoptions.py
photoshop_object_model/gallerysecurityoptions.py
photoshop_object_model/gallerythumbnailoptions.py
photoshop_object_model/gifsaveoptions.py
photoshop_object_model/graycolor.py
photoshop_object_model/historystate.py
photoshop_object_model/historystates.py
photoshop_object_model/hsbcolor.py
photoshop_object_model/indexedconversionoptions.py
photoshop_object_model/jpegsaveoptions.py
photoshop_object_model/labcolor.py
photoshop_object_model/layercomp.py
photoshop_object_model/layercomps.py
photoshop_object_model/layers.py
photoshop_object_model/layerset.py
photoshop_object_model/layersets.py
photoshop_object_model/measurementlog.py
photoshop_object_model/measurementscale.py
photoshop_object_model-0.0.3.dist-info/LICENSE
photoshop_object_model-0.0.3.dist-info/METADATA
photoshop_object_model-0.0.3.dist-info/WHEEL
photoshop_object_model-0.0.3.dist-info/top_level.txt
photoshop_object_model-0.0.3.dist-info/RECORD
