Metadata-Version: 2.1
Name: photoshop-object-model
Version: 0.0.3
Summary: Photoshop Object Model
Author: Tristan Languebien
Author-email: <tlanguebien@gmail.com>
Keywords: python,photoshop
Classifier: Development Status :: 1 - Planning
Classifier: Intended Audience :: Developers
Classifier: Programming Language :: Python :: 3
Classifier: Operating System :: Microsoft :: Windows
License-File: LICENSE
